{
  "openapi": "3.0.0",
  "info": {
    "version": "1.0.0",
    "title": "REST API",
    "description": ""
  },
  "servers": [
    {
      "url": "",
      "description": "local server"
    }
  ],
  "tags": [
    {
      "name": "Tests",
      "description": ""
    }
  ],
  "paths": {
    "/test/": {
      "get": {
        "tags": [
          "Tests"
        ],
        "description": "",
        "responses": {
          "200": {
            "description": "OK"
          }
        }
      },
      "post": {
        "description": "",
        "responses": {
          "200": {
            "description": "OK"
          }
        }
      }
    }
  }
}